zzzz.py
zzzz-0.0.3.dist-info/METADATA
zzzz-0.0.3.dist-info/WHEEL
zzzz-0.0.3.dist-info/entry_points.txt
zzzz-0.0.3.dist-info/top_level.txt
zzzz-0.0.3.dist-info/RECORD
