Metadata-Version: 2.1
Name: zzzz
Version: 0.0.3
Summary: print("zzzz")
Home-page: UNKNOWN
Author: suiting
Author-email: yukater@outlook.com
License: UNKNOWN
Platform: UNKNOWN
